README.md
setup.cfg
setup.py
particle_tracker_one_d/__init__.py
particle_tracker_one_d.egg-info/PKG-INFO
particle_tracker_one_d.egg-info/SOURCES.txt
particle_tracker_one_d.egg-info/dependency_links.txt
particle_tracker_one_d.egg-info/not-zip-safe
particle_tracker_one_d.egg-info/requires.txt
particle_tracker_one_d.egg-info/top_level.txt
particle_tracker_one_d/frames/__init__.py
particle_tracker_one_d/frames/frames.py
particle_tracker_one_d/hindrance/__init__.py
particle_tracker_one_d/hindrance/hindrance_factor.py
particle_tracker_one_d/particle_tracker/__init__.py
particle_tracker_one_d/particle_tracker/particle_tracker.py
particle_tracker_one_d/shortest_path_finder/__init__.py
particle_tracker_one_d/shortest_path_finder/shortest_path_finder.py
particle_tracker_one_d/trajectory/__init__.py
particle_tracker_one_d/trajectory/trajectory.py
tests/__init__.py
tests/integration/__init__.py
tests/integration/test_adding_trajectories.py
tests/unit/__init__.py
tests/unit/test_frames.py
tests/unit/test_particle_tracker.py
tests/unit/test_shortest_path_finder.py
tests/unit/test_trajectory.py