Metadata-Version: 2.1
Name: particle-tracker-one-d
Version: 0.5.6
Summary: Particle tracking in Kymographs
Home-page: UNKNOWN
Author: Johan Tenghamn
Author-email: tenghamn@chalmers.se
License: MIT
Keywords: particle tracking nanochannel
Platform: UNKNOWN
Classifier: Development Status :: 4 - Beta
Classifier: Programming Language :: Python :: 3.6
Classifier: Intended Audience :: Science/Research
Classifier: Topic :: Scientific/Engineering :: Physics
